ssb_pypitest_rav/__init__.py
ssb_pypitest_rav/__main__.py
ssb_pypitest_rav/functions.py
ssb_pypitest_rav/py.typed
ssb_pypitest_rav-0.0.2.dist-info/LICENSE
ssb_pypitest_rav-0.0.2.dist-info/METADATA
ssb_pypitest_rav-0.0.2.dist-info/WHEEL
ssb_pypitest_rav-0.0.2.dist-info/entry_points.txt
ssb_pypitest_rav-0.0.2.dist-info/RECORD
