Metadata-Version: 2.3
Name: ssb-pypitest-rav
Version: 0.0.2
Summary: SSB Pypitest Rav
License: MIT
Author: Roar Vålen
Author-email: rav@ssb.no
Requires-Python: >=3.10,<4.0
Classifier: Development Status :: 4 - Beta
Classifier: License :: OSI Approved :: MIT License
Classifier: Programming Language :: Python :: 3
Classifier: Programming Language :: Python :: 3.10
Classifier: Programming Language :: Python :: 3.11
Classifier: Programming Language :: Python :: 3.12
Classifier: Programming Language :: Python :: 3.13
Requires-Dist: click (>=8.0.1)
Project-URL: Changelog, https://github.com/statisticsnorway/ssb-pypitest-rav/releases
Project-URL: Documentation, https://statisticsnorway.github.io/ssb-pypitest-rav
Project-URL: Homepage, https://github.com/statisticsnorway/ssb-pypitest-rav
Project-URL: Repository, https://github.com/statisticsnorway/ssb-pypitest-rav
